oxlab/__init__.py
oxlab/github.py
oxlab-0.3.1.dist-info/LICENSE.txt
oxlab-0.3.1.dist-info/METADATA
oxlab-0.3.1.dist-info/WHEEL
oxlab-0.3.1.dist-info/entry_points.txt
oxlab-0.3.1.dist-info/top_level.txt
oxlab-0.3.1.dist-info/RECORD
