Metadata-Version: 2.1
Name: oxlab
Version: 0.3.1
Summary: Tools for Google Colab and Jupyter notebooks.
Home-page: http://github.com/emin63/oxlab
Author: Emin Martinian
Author-email: emin.martinian@gmail.com
License: License :: OSI Approved :: MIT License
Keywords: google colab jupyter notebooks
Classifier: Development Status :: 3 - Alpha
Classifier: Intended Audience :: Developers
Classifier: Programming Language :: Python :: 3
License-File: LICENSE.txt
